{
	"name": "Twos",
	"tag": "twos",
	"weights": {
		"dev": 1.0,
		"spd": 2.0,
		"mem": 1.0
	},
	"description": "<p>Given a positive integern and digit k, find the number of times the digit k appears in the inclusive range [0, n].</p>",
	"sample": {
		"test_cases": [
			"25 2",
			"99 0",
			"1337 9",
			"42 1"
		],
		"solutions": [
			"9",
			"10",
			"363",
			"15"
		]
	},
	"official": {
		"test_cases": [
			"3529 9",
			"8162 9",
			"7503 9",
			"3076 3",
			"5439 3",
			"5815 9",
			"2178 2",
			"4085 5",
			"8387 5",
			"9457 2",
			"7857 1",
			"1887 8",
			"1229 5",
			"229 2",
			"9033 1",
			"1997 6",
			"7274 2",
			"5219 9",
			"7717 1",
			"6360 9",
			"759 1",
			"1613 8",
			"5656 6",
			"4662 0",
			"7304 0",
			"7623 3",
			"9753 3",
			"9612 5",
			"1635 0",
			"8246 9",
			"6451 8",
			"9713 2",
			"2884 1",
			"8504 4",
			"6574 0",
			"4451 7",
			"702 3",
			"763 4",
			"6929 3",
			"5199 3",
			"1813 4",
			"4154 1",
			"2694 1",
			"90 0",
			"8277 9",
			"9166 1",
			"6294 8",
			"195 5",
			"751 3",
			"4065 8",
			"1298 7",
			"9269 5",
			"8607 2",
			"3362 2",
			"2680 6",
			"4697 9",
			"7015 5",
			"7741 4",
			"7772 9",
			"7853 4",
			"450 3",
			"5836 8",
			"4519 3",
			"4173 8",
			"4866 0",
			"272 8",
			"5338 1",
			"4278 4",
			"722 6",
			"468 4",
			"4437 3",
			"7367 4",
			"7825 7",
			"952 7",
			"5355 6",
			"5737 5",
			"5473 8",
			"6209 0",
			"2300 4",
			"6263 9",
			"6074 5",
			"7018 4",
			"3884 6",
			"3212 5",
			"5900 9",
			"536 5",
			"7902 9",
			"6884 3",
			"472 7",
			"8944 5",
			"6929 1",
			"277 5",
			"8558 6",
			"1709 2",
			"45 9",
			"223 0",
			"6147 1",
			"2044 3",
			"2562 4",
			"4028 5"
		],
		"solutions": [
			"1003",
			"2426",
			"2200",
			"995",
			"2694",
			"1661",
			"817",
			"1219",
			"3479",
			"3896",
			"3376",
			"564",
			"343",
			"83",
			"3714",
			"600",
			"3233",
			"1542",
			"3350",
			"1866",
			"256",
			"421",
			"1683",
			"1327",
			"2156",
			"3323",
			"3956",
			"3921",
			"424",
			"2444",
			"1885",
			"3942",
			"1879",
			"3601",
			"1908",
			"1285",
			"240",
			"256",
			"3083",
			"2540",
			"561",
			"2291",
			"1840",
			"10",
			"2447",
			"3804",
			"1859",
			"40",
			"255",
			"1206",
			"360",
			"3757",
			"3621",
			"2077",
			"819",
			"1337",
			"3102",
			"3346",
			"2247",
			"3375",
			"195",
			"1700",
			"2402",
			"1227",
			"1367",
			"47",
			"2674",
			"1537",
			"242",
			"166",
			"2392",
			"3177",
			"3188",
			"285",
			"1565",
			"2482",
			"1587",
			"1841",
			"660",
			"1846",
			"2817",
			"3102",
			"1178",
			"941",
			"1681",
			"141",
			"2283",
			"3079",
			"90",
			"3684",
			"3093",
			"58",
			"3506",
			"541",
			"4",
			"43",
			"2883",
			"615",
			"816",
			"1203"
		]
	}
}